Metadata-Version: 2.1
Name: oligoss
Version: 0.0.3
Summary: de novo sequencer for heterogeneous oligomer mixtures
Home-page: UNKNOWN
Author: ALife Team, Cronin Group
Author-email: daviddoran20161@gmail.com
License: AGPLv3
Platform: UNKNOWN
Classifier: Programming Language :: Python :: 3
Classifier: Programming Language :: Python :: 3.7
Classifier: License :: OSI Approved :: GNU Affero General Public License v3 or later (AGPLv3+)
Classifier: Operating System :: Unix
Classifier: Development Status :: 3 - Alpha
Requires-Dist: bson
Requires-Dist: psutil
Requires-Dist: mzmlripper
Requires-Dist: pymongo
